README.rst
setup.py
pytest_expect/__init__.py
pytest_expect/expect.py
pytest_expect.egg-info/PKG-INFO
pytest_expect.egg-info/SOURCES.txt
pytest_expect.egg-info/dependency_links.txt
pytest_expect.egg-info/entry_points.txt
pytest_expect.egg-info/requires.txt
pytest_expect.egg-info/top_level.txt